mew/__init__.py
mew/codes.py
gengar-0.1.2.dist-info/METADATA
gengar-0.1.2.dist-info/WHEEL
gengar-0.1.2.dist-info/top_level.txt
gengar-0.1.2.dist-info/RECORD
